noop.cpython-311-darwin.so
sqlite_html/__init__.py
sqlite_html/html0.dylib
sqlite_html/version.py
sqlite_html-0.1.3.dist-info/METADATA
sqlite_html-0.1.3.dist-info/WHEEL
sqlite_html-0.1.3.dist-info/top_level.txt
sqlite_html-0.1.3.dist-info/RECORD
