Metadata-Version: 2.1
Name: sqlite-html
Version: 0.1.3
Home-page: https://github.com/asg017/sqlite-html
Author: Alex Garcia
License: MIT License, Apache License, Version 2.0
Project-URL: Issues, https://github.com/asg017/sqlite-html/issues
Project-URL: CI, https://github.com/asg017/sqlite-html/actions
Project-URL: Changelog, https://github.com/asg017/sqlite-html/releases
Requires-Python: >=3.7
Provides-Extra: test
Requires-Dist: pytest ; extra == 'test'
